{"display":{"thirdperson_lefthand":{}},"elements":[{"from":[3.2566147,-7.7569027,5.5524683],"to":[9.760059,9.152054,13.356602],"rotation":{"origin":[6.508337,4.599642,9.454535],"axis":"x","angle":-22.5},"faces":{"west":{"uv":[7.375,10.25,7.75,11.0625],"texture":"#0","tintindex":0},"down":{"uv":[12.1875,10.5,11.875,10.875],"texture":"#0","tintindex":0},"north":{"uv":[11.0,8.9375,11.3125,9.75],"texture":"#0","tintindex":0},"up":{"uv":[12.1875,10.5,11.875,10.125],"texture":"#0","tintindex":0},"south":{"uv":[9.8125,11.0,10.125,11.8125],"texture":"#0","tintindex":0},"east":{"uv":[7.0,10.25,7.375,11.0625],"texture":"#0","tintindex":0}}},{"from":[6.19018,-1.1627693,2.259163],"to":[6.19018,0.7882633,8.112263],"rotation":{"origin":[7.221427,14.331852,-25.772705],"axis":"z","angle":0.0},"faces":{"west":{"uv":[12.65625,4.1875,12.375,4.28125],"texture":"#0","tintindex":0},"down":{"uv":[0.0,0.0,0.0,0.28125],"texture":"#0","tintindex":0},"north":{"uv":[0.0,0.0,0.0,0.09375],"texture":"#0","tintindex":0},"up":{"uv":[0.0,0.28125,0.0,0.0],"texture":"#0","tintindex":0},"south":{"uv":[0.0,0.0,0.0,0.09375],"texture":"#0","tintindex":0},"east":{"uv":[12.375,4.4375,12.65625,4.53125],"texture":"#0","tintindex":0}}},{"from":[6.19018,9.357983,-2.8053951],"to":[6.19018,11.309015,3.0477052],"rotation":{"origin":[-4.778574,4.266817,1.5769515],"axis":"x","angle":45.0},"faces":{"west":{"uv":[12.65625,4.1875,12.375,4.28125],"texture":"#0","tintindex":0},"down":{"uv":[0.0,0.0,0.0,0.28125],"texture":"#0","tintindex":0},"north":{"uv":[0.0,0.0,0.0,0.09375],"texture":"#0","tintindex":0},"up":{"uv":[0.0,0.28125,0.0,0.0],"texture":"#0","tintindex":0},"south":{"uv":[0.0,0.0,0.0,0.09375],"texture":"#0","tintindex":0},"east":{"uv":[12.375,5.375,12.65625,5.46875],"texture":"#0","tintindex":0}}},{"from":[6.1902103,8.20503,-0.9319439],"to":[6.1902103,10.156065,4.921157],"rotation":{"origin":[-30.803055,6.1805477,-3.005394],"axis":"x","angle":22.5},"faces":{"west":{"uv":[12.65625,4.1875,12.375,4.28125],"texture":"#0","tintindex":0},"down":{"uv":[0.0,0.0,0.0,0.28125],"texture":"#0","tintindex":0},"north":{"uv":[0.0,0.0,0.0,0.09375],"texture":"#0","tintindex":0},"up":{"uv":[0.0,0.28125,0.0,0.0],"texture":"#0","tintindex":0},"south":{"uv":[0.0,0.0,0.0,0.09375],"texture":"#0","tintindex":0},"east":{"uv":[12.375,2.8125,12.65625,2.90625],"texture":"#0","tintindex":0}}},{"from":[6.19018,3.82864,1.6694345],"to":[6.19018,5.7796745,7.5225344],"rotation":{"origin":[3.1969433,5.1805477,0.59598494],"axis":"x","angle":22.5},"faces":{"west":{"uv":[12.65625,4.1875,12.375,4.28125],"texture":"#0","tintindex":0},"down":{"uv":[0.0,0.0,0.0,0.28125],"texture":"#0","tintindex":0},"north":{"uv":[0.0,0.0,0.0,0.09375],"texture":"#0","tintindex":0},"up":{"uv":[0.0,0.28125,0.0,0.0],"texture":"#0","tintindex":0},"south":{"uv":[0.0,0.0,0.0,0.09375],"texture":"#0","tintindex":0},"east":{"uv":[12.375,4.1875,12.65625,4.28125],"texture":"#0","tintindex":0}}}],"textures":{"1":"wakame:cursed_dragon/cursed_dragon"}}