{"display":{"thirdperson_lefthand":{"scale":[2.4618225,2.4618225,2.4618225]}},"elements":[{"from":[-7.0104933,6.815378,5.1905937],"to":[5.9880066,9.252597,7.6278124],"rotation":{"origin":[1.5007501,8.0,15.514757],"axis":"y","angle":-22.5},"faces":{"up":{"uv":[8.5,5.5,7.75,1.5],"texture":"#2","rotation":270,"tintindex":0},"north":{"uv":[7.75,0.0,11.75,0.75],"texture":"#2","tintindex":0},"east":{"uv":[9.75,10.5,10.5,11.25],"texture":"#2","tintindex":0},"south":{"uv":[7.75,0.75,11.75,1.5],"texture":"#2","tintindex":0},"down":{"uv":[8.5,5.5,7.75,9.5],"texture":"#2","rotation":90,"tintindex":0},"west":{"uv":[9.0,10.5,9.75,11.25],"texture":"#2","tintindex":0}}},{"from":[6.6336217,7.01848,9.092345],"to":[8.664638,9.049496,16.404001],"rotation":{"origin":[1.5007501,8.0,15.514757],"axis":"z","angle":0.0},"faces":{"up":{"uv":[10.125,9.25,9.5,7.0],"texture":"#2","tintindex":0},"north":{"uv":[10.5,10.625,11.125,11.25],"texture":"#2","tintindex":0},"east":{"uv":[9.5,5.5,11.75,6.125],"texture":"#2","tintindex":0},"south":{"uv":[10.75,7.125,11.375,7.75],"texture":"#2","tintindex":0},"down":{"uv":[8.375,9.5,7.75,11.75],"texture":"#2","tintindex":0},"west":{"uv":[9.5,6.25,11.75,6.875],"texture":"#2","tintindex":0}}},{"from":[6.2275686,7.424683,18.300575],"to":[7.4461784,8.643292,25.612234],"rotation":{"origin":[1.5007501,8.0,15.514757],"axis":"y","angle":22.5},"faces":{"up":{"uv":[10.625,9.25,10.25,7.0],"texture":"#2","tintindex":0},"north":{"uv":[10.75,9.25,11.125,9.625],"texture":"#2","tintindex":0},"east":{"uv":[8.5,9.625,10.75,10.0],"texture":"#2","tintindex":0},"south":{"uv":[10.75,9.75,11.125,10.125],"texture":"#2","tintindex":0},"down":{"uv":[8.875,10.5,8.5,12.75],"texture":"#2","tintindex":0},"west":{"uv":[8.5,10.125,10.75,10.5],"texture":"#2","tintindex":0}}},{"from":[-7.0104933,7.01848,7.6278124],"to":[-4.979478,9.049496,20.626312],"rotation":{"origin":[1.5007501,8.0,15.514757],"axis":"y","angle":-22.5},"faces":{"up":{"uv":[12.5,3.625,8.5,3.0],"texture":"#2","rotation":270,"tintindex":0},"north":{"uv":[10.75,7.875,11.375,8.5],"texture":"#2","tintindex":0},"east":{"uv":[8.5,2.25,12.5,2.875],"texture":"#2","tintindex":0},"south":{"uv":[10.75,8.625,11.375,9.25],"texture":"#2","tintindex":0},"down":{"uv":[12.5,3.75,8.5,4.375],"texture":"#2","rotation":90,"tintindex":0},"west":{"uv":[8.5,1.5,12.5,2.125],"texture":"#2","tintindex":0}}},{"from":[-7.9125195,7.424683,16.980106],"to":[-6.6939096,8.643292,29.978607],"rotation":{"origin":[1.5007501,8.0,15.514757],"axis":"z","angle":0.0},"faces":{"up":{"uv":[8.875,9.5,8.5,5.5],"texture":"#2","tintindex":0},"north":{"uv":[0.0,11.0,0.375,11.4375],"texture":"#2","tintindex":0},"east":{"uv":[8.5,4.625,12.5,5.0],"texture":"#2","tintindex":0},"south":{"uv":[0.5,11.0,0.875,11.375],"texture":"#2","tintindex":0},"down":{"uv":[9.375,5.5,9.0,9.5],"texture":"#2","tintindex":0},"west":{"uv":[8.5,5.125,12.5,5.5],"texture":"#2","tintindex":0}}},{"from":[-5.7918844,7.826012,6.8154063],"to":[12.081053,7.8341355,32.0],"rotation":{"origin":[1.5007501,8.0,15.514757],"axis":"y","angle":-22.5},"faces":{"up":{"uv":[7.75,5.5,0.0,0.0],"texture":"#2","rotation":270,"tintindex":0},"north":{"uv":[0.0,0.0,5.5,0.0],"texture":"#2","tintindex":0},"east":{"uv":[0.0,0.0,7.75,0.0],"texture":"#2","tintindex":0},"south":{"uv":[0.0,0.0,5.5,0.0],"texture":"#2","tintindex":0},"down":{"uv":[7.75,5.5,0.0,11.0],"texture":"#2","rotation":90,"tintindex":0},"west":{"uv":[0.0,0.0,7.75,0.0],"texture":"#2","tintindex":0}}}],"textures":{"0":"wakame:dragon/head","1":"wakame:dragon/front","2":"wakame:dragon/wing","3":"wakame:dragon/neck","4":"wakame:dragon/body","5":"wakame:dragon/fleg","6":"wakame:dragon/b_leg","7":"wakame:dragon/tail"}}